dorado/__init__.py
dorado/_astropy_init.py
dorado/astropho.py
dorado/conftest.py
dorado/dorado.py
dorado/fournax.py
dorado/graf.py
dorado/imreduc.py
dorado/lazyeye.py
dorado/phanal.py
dorado/rchive.py
dorado/teleanal.py
dorado/version.py
dorado/YESpy/__init__.py
dorado/data/README.rst
dorado/example_subpkg/__init__.py
dorado/example_subpkg/setup_package.py
dorado/example_subpkg/tests/__init__.py
dorado/extern/__init__.py
dorado/fournax/__init__.py
dorado/fournax/fitt.py
dorado/fournax/fournax.py
dorado/imreduc/__init__.py
dorado/imreduc/imreduc.py
dorado/imreduc/red.py
dorado/lazyeye/__init__.py
dorado/lazyeye/eyeon.py
dorado/lazyeye/lazyeye.py
dorado/rchive/__init__.py
dorado/rchive/file_high.py
dorado/rchive/rchive.py
dorado/tests/__init__.py
dorado/tests/test_example.py
dorado/utils/__init__.py
dorado/utils/tests/__init__.py
dorado/vizual/__init__.py
dorado/vizual/graf.py
dorado/waldo/__init__.py
dorado/waldo/waldo.py
dorado/waldo/where.py
dorado-1.2.0.dist-info/LICENSE.rst
dorado-1.2.0.dist-info/METADATA
dorado-1.2.0.dist-info/WHEEL
dorado-1.2.0.dist-info/entry_points.txt
dorado-1.2.0.dist-info/top_level.txt
dorado-1.2.0.dist-info/RECORD
