Metadata-Version: 2.1
Name: dorado
Version: 1.2.0
Summary: Digitized Observatory Resources for Automated Data Operations
Home-page: https://github.com/Mucephie/DORADO
Author: Mucephie
Author-email: mucephie@my.yorku.ca
License: BSD 3-Clause
Platform: UNKNOWN
Requires-Python: >=3.6
Requires-Dist: astropy
Requires-Dist: numpy
Requires-Dist: scipy
Requires-Dist: scikit-image
Requires-Dist: astroquery
Requires-Dist: matplotlib
Requires-Dist: ccdproc
Requires-Dist: photutils
Requires-Dist: astroalign
Provides-Extra: all
Requires-Dist: astroalign ; extra == 'all'
Provides-Extra: docs
Requires-Dist: sphinx-astropy ; extra == 'docs'
Provides-Extra: test
Requires-Dist: pytest-astropy ; extra == 'test'
